kimiko_objects/__init__.py
kimiko_objects/objects.py
kimiko_objects-0.0.4.dist-info/LICENSE
kimiko_objects-0.0.4.dist-info/METADATA
kimiko_objects-0.0.4.dist-info/WHEEL
kimiko_objects-0.0.4.dist-info/top_level.txt
kimiko_objects-0.0.4.dist-info/RECORD
