Metadata-Version: 2.1
Name: kimiko-objects
Version: 0.0.4
Summary: Standard way for interacting with Kimiko objects
Home-page: UNKNOWN
Author: Kimiko, Inc.
Author-email: chris@kimiko.io
License: UNKNOWN
Platform: UNKNOWN
Classifier: Programming Language :: Python :: 3
Classifier: Operating System :: OS Independent
Requires-Python: >=3.9
License-File: LICENSE
